pikapika_organizer/__init__.py
pikapika_organizer-0.9.0.dist-info/licenses/LICENSE
pikapika_organizer-0.9.0.dist-info/METADATA
pikapika_organizer-0.9.0.dist-info/WHEEL
pikapika_organizer-0.9.0.dist-info/entry_points.txt
pikapika_organizer-0.9.0.dist-info/top_level.txt
pikapika_organizer-0.9.0.dist-info/RECORD
