Metadata-Version: 2.4
Name: pikapika-organizer
Version: 0.9.0
Summary: Pikapika - A Python CLI utility to organize your files by extension
Author-email: Ariz Muajianisan <arizmuajianisan@gmail.com>
Maintainer-email: Ariz Muajianisan <arizmuajianisan@gmail.com>
License-Expression: MIT
Project-URL: Homepage, https://arizmuajianisan.github.io/pikapika
Project-URL: Repository, https://github.com/arizmuajianisan/pikapika
Project-URL: Bug Reports, https://github.com/arizmuajianisan/pikapika/issues
Keywords: cli,file-organizer,downloads,cleanup,automation
Classifier: Programming Language :: Python :: 3
Classifier: Programming Language :: Python :: 3.13
Classifier: Programming Language :: Python :: 3.14
Classifier: Operating System :: OS Independent
Classifier: Development Status :: 4 - Beta
Classifier: Topic :: Utilities
Classifier: Topic :: System :: Filesystems
Classifier: Intended Audience :: End Users/Desktop
Classifier: Environment :: Console
Requires-Python: >=3.13
License-File: LICENSE
Requires-Dist: send2trash>=1.8.0
Provides-Extra: dev
Requires-Dist: pytest>=9.0.2; extra == "dev"
Requires-Dist: ruff>=0.14.10; extra == "dev"
Dynamic: license-file
